README.md
setup.py
sw_pulumi_algolia/__init__.py
sw_pulumi_algolia/_utilities.py
sw_pulumi_algolia/api_key.py
sw_pulumi_algolia/get_index.py
sw_pulumi_algolia/index.py
sw_pulumi_algolia/outputs.py
sw_pulumi_algolia/provider.py
sw_pulumi_algolia/pulumi-plugin.json
sw_pulumi_algolia/py.typed
sw_pulumi_algolia.egg-info/PKG-INFO
sw_pulumi_algolia.egg-info/SOURCES.txt
sw_pulumi_algolia.egg-info/dependency_links.txt
sw_pulumi_algolia.egg-info/not-zip-safe
sw_pulumi_algolia.egg-info/requires.txt
sw_pulumi_algolia.egg-info/top_level.txt
sw_pulumi_algolia/config/__init__.py
sw_pulumi_algolia/config/vars.py