Metadata-Version: 2.1
Name: sw-pulumi-algolia
Version: 0.1.1
Summary: A Pulumi package for creating and managing algolia cloud resources.
Home-page: https://www.pulumi.com
License: Apache-2.0
Project-URL: Repository, https://github.com/swarm-work/pulumi-algolia
Keywords: pulumi algolia category/cloud
Platform: UNKNOWN
